<annotation>
	<folder>image</folder>
	<filename>Bengal_1039.jpg</filename>
	<path>/Users/xiaoluzhang/Dropbox/Others/Dataset/image/Bengal_1039.jpg</path>
	<source>
		<database>Unknown</database>
	</source>
	<size>
		<width>640</width>
		<height>800</height>
		<depth>3</depth>
	</size>
	<segmented>0</segmented>
	<object>
		<name>Bengal</name>
		<pose>Unspecified</pose>
		<truncated>0</truncated>
		<difficult>0</difficult>
		<bndbox>
			<xmin>92</xmin>
			<ymin>6</ymin>
			<xmax>619</xmax>
			<ymax>530</ymax>
		</bndbox>
	</object>
</annotation>