<annotation>
	<folder>image</folder>
	<filename>Bengal_1434.jpg</filename>
	<path>/Users/xiaoluzhang/Dropbox/Others/Dataset/image/Bengal_1434.jpg</path>
	<source>
		<database>Unknown</database>
	</source>
	<size>
		<width>1620</width>
		<height>1080</height>
		<depth>3</depth>
	</size>
	<segmented>0</segmented>
	<object>
		<name>Bengal</name>
		<pose>Unspecified</pose>
		<truncated>0</truncated>
		<difficult>0</difficult>
		<bndbox>
			<xmin>180</xmin>
			<ymin>83</ymin>
			<xmax>925</xmax>
			<ymax>945</ymax>
		</bndbox>
	</object>
	<object>
		<name>Bengal</name>
		<pose>Unspecified</pose>
		<truncated>0</truncated>
		<difficult>0</difficult>
		<bndbox>
			<xmin>897</xmin>
			<ymin>83</ymin>
			<xmax>1608</xmax>
			<ymax>951</ymax>
		</bndbox>
	</object>
</annotation>