<annotation verified="yes">
	<folder>image</folder>
	<filename>Bengal_1362.jpg</filename>
	<path>/Users/xiaoluzhang/Dropbox/Others/Dataset/image/Bengal_1362.jpg</path>
	<source>
		<database>Unknown</database>
	</source>
	<size>
		<width>4774</width>
		<height>3181</height>
		<depth>3</depth>
	</size>
	<segmented>0</segmented>
	<object>
		<name>Bengal</name>
		<pose>Unspecified</pose>
		<truncated>0</truncated>
		<difficult>0</difficult>
		<bndbox>
			<xmin>915</xmin>
			<ymin>129</ymin>
			<xmax>4303</xmax>
			<ymax>2029</ymax>
		</bndbox>
	</object>
</annotation>