<annotation>
	<folder>image</folder>
	<filename>Bengal_1135.jpg</filename>
	<path>/Users/xiaoluzhang/Dropbox/Others/Dataset/image/Bengal_1135.jpg</path>
	<source>
		<database>Unknown</database>
	</source>
	<size>
		<width>2592</width>
		<height>1728</height>
		<depth>3</depth>
	</size>
	<segmented>0</segmented>
	<object>
		<name>Bengal</name>
		<pose>Unspecified</pose>
		<truncated>1</truncated>
		<difficult>0</difficult>
		<bndbox>
			<xmin>499</xmin>
			<ymin>205</ymin>
			<xmax>2592</xmax>
			<ymax>1709</ymax>
		</bndbox>
	</object>
</annotation>