<annotation>
	<folder>image</folder>
	<filename>Birman_1444.jpg</filename>
	<path>/Users/xiaoluzhang/Dropbox/Others/Dataset/image/Birman_1444.jpg</path>
	<source>
		<database>Unknown</database>
	</source>
	<size>
		<width>5472</width>
		<height>3648</height>
		<depth>3</depth>
	</size>
	<segmented>0</segmented>
	<object>
		<name>Birman</name>
		<pose>Unspecified</pose>
		<truncated>0</truncated>
		<difficult>0</difficult>
		<bndbox>
			<xmin>67</xmin>
			<ymin>93</ymin>
			<xmax>5004</xmax>
			<ymax>3330</ymax>
		</bndbox>
	</object>
</annotation>