<annotation>
	<folder>image</folder>
	<filename>Birman_1026.jpg</filename>
	<path>/Users/xiaoluzhang/Dropbox/Others/Dataset/image/Birman_1026.jpg</path>
	<source>
		<database>Unknown</database>
	</source>
	<size>
		<width>670</width>
		<height>472</height>
		<depth>3</depth>
	</size>
	<segmented>0</segmented>
	<object>
		<name>Birman</name>
		<pose>Unspecified</pose>
		<truncated>0</truncated>
		<difficult>0</difficult>
		<bndbox>
			<xmin>211</xmin>
			<ymin>61</ymin>
			<xmax>497</xmax>
			<ymax>455</ymax>
		</bndbox>
	</object>
</annotation>