<annotation>
	<folder>image</folder>
	<filename>Bombay_1151.jpg</filename>
	<path>/Users/xiaoluzhang/Dropbox/Others/Dataset/image/Bombay_1151.jpg</path>
	<source>
		<database>Unknown</database>
	</source>
	<size>
		<width>4372</width>
		<height>2906</height>
		<depth>3</depth>
	</size>
	<segmented>0</segmented>
	<object>
		<name>Bombay</name>
		<pose>Unspecified</pose>
		<truncated>0</truncated>
		<difficult>0</difficult>
		<bndbox>
			<xmin>881</xmin>
			<ymin>418</ymin>
			<xmax>4071</xmax>
			<ymax>2748</ymax>
		</bndbox>
	</object>
</annotation>