<annotation>
	<folder>image</folder>
	<filename>Russian_blue_1298.jpg</filename>
	<path>/Users/xiaoluzhang/Dropbox/Others/Dataset/image_todo/Russian_blue_1298.jpg</path>
	<source>
		<database>Unknown</database>
	</source>
	<size>
		<width>2048</width>
		<height>1536</height>
		<depth>3</depth>
	</size>
	<segmented>0</segmented>
	<object>
		<name>Russian_blue</name>
		<pose>Unspecified</pose>
		<truncated>0</truncated>
		<difficult>0</difficult>
		<bndbox>
			<xmin>10</xmin>
			<ymin>262</ymin>
			<xmax>2026</xmax>
			<ymax>1366</ymax>
		</bndbox>
	</object>
</annotation>