<annotation>
	<folder>image</folder>
	<filename>Russian_blue_1045.jpg</filename>
	<path>/Users/xiaoluzhang/Dropbox/Others/Dataset/image_todo/Russian_blue_1045.jpg</path>
	<source>
		<database>Unknown</database>
	</source>
	<size>
		<width>600</width>
		<height>400</height>
		<depth>3</depth>
	</size>
	<segmented>0</segmented>
	<object>
		<name>Russian_blue</name>
		<pose>Unspecified</pose>
		<truncated>0</truncated>
		<difficult>0</difficult>
		<bndbox>
			<xmin>75</xmin>
			<ymin>27</ymin>
			<xmax>509</xmax>
			<ymax>381</ymax>
		</bndbox>
	</object>
</annotation>