<annotation>
	<folder>image</folder>
	<filename>Sphynx_1486.jpg</filename>
	<path>/Users/xiaoluzhang/Dropbox/Others/Dataset/image_todo/Sphynx_1486.jpg</path>
	<source>
		<database>Unknown</database>
	</source>
	<size>
		<width>788</width>
		<height>581</height>
		<depth>3</depth>
	</size>
	<segmented>0</segmented>
	<object>
		<name>Sphynx</name>
		<pose>Unspecified</pose>
		<truncated>0</truncated>
		<difficult>0</difficult>
		<bndbox>
			<xmin>229</xmin>
			<ymin>70</ymin>
			<xmax>513</xmax>
			<ymax>479</ymax>
		</bndbox>
	</object>
</annotation>