<annotation>
	<folder>image</folder>
	<filename>Sphynx_1522.jpg</filename>
	<path>/Users/xiaoluzhang/Dropbox/Others/Dataset/image_todo/Sphynx_1522.jpg</path>
	<source>
		<database>Unknown</database>
	</source>
	<size>
		<width>4608</width>
		<height>3072</height>
		<depth>3</depth>
	</size>
	<segmented>0</segmented>
	<object>
		<name>Sphynx</name>
		<pose>Unspecified</pose>
		<truncated>0</truncated>
		<difficult>0</difficult>
		<bndbox>
			<xmin>47</xmin>
			<ymin>352</ymin>
			<xmax>4104</xmax>
			<ymax>2297</ymax>
		</bndbox>
	</object>
</annotation>